AUTHORS.rst
CONTRIBUTING.rst
HISTORY.rst
LICENSE
MANIFEST.in
README.rst
dictionary
pyxkcdpass.py
setup.cfg
setup.py
docs/Makefile
docs/authors.rst
docs/conf.py
docs/contributing.rst
docs/history.rst
docs/index.rst
docs/installation.rst
docs/make.bat
docs/readme.rst
docs/usage.rst
pyxkcdpass.egg-info/PKG-INFO
pyxkcdpass.egg-info/SOURCES.txt
pyxkcdpass.egg-info/dependency_links.txt
pyxkcdpass.egg-info/entry_points.txt
pyxkcdpass.egg-info/not-zip-safe
pyxkcdpass.egg-info/top_level.txt
tests/__init__.py
tests/test_pyxkcdpass.py