Metadata-Version: 1.1
Name: pyxkcdpass
Version: 0.2.0
Summary: This script provides a simple way to generate secure and human readable passwords, based on XKCD #936
Home-page: https://github.com/ikkebr/pyxkcdpass
Author: Henrique Pereira
Author-email: ikkibr@gmail.com
License: BSD
Keywords: pyxkcdpass
Platform: UNKNOWN
Classifier: Development Status :: 4 - Beta
Classifier: Intended Audience :: Developers
Classifier: License :: OSI Approved :: BSD License
Classifier: Natural Language :: English
Classifier: Programming Language :: Python :: 2
Classifier: Programming Language :: Python :: 2.6
Classifier: Programming Language :: Python :: 2.7
Classifier: Programming Language :: Python :: 3
Classifier: Programming Language :: Python :: 3.3
